{"sections":{"image_with_text_overlay_XyHULG":{"type":"image-with-text-overlay","blocks":{"spacing_37BKB9":{"type":"spacing","settings":{"height":0,"height_mobile":12}},"image_PXaXT7":{"type":"image","settings":{"image":"shopify:\/\/shop_images\/frozen_rocket_svg_website_w.svg","image_width":"custom","image_max_width":210,"image_max_width_mobile":160}},"spacing_WNNqbL":{"type":"spacing","settings":{"height":0,"height_mobile":80}},"spacing_GJ6dRp":{"type":"spacing","settings":{"height":0,"height_mobile":120}},"spacing_dextkm":{"type":"spacing","settings":{"height":0,"height_mobile":120}},"button_fHNQ7J":{"type":"button","settings":{"button_label":"SHOP NOW","button_link":"shopify:\/\/pages\/shop-by-collection","button_style":"primary","button_size":"sm","button_external":false,"button_icon":true}}},"block_order":["spacing_37BKB9","image_PXaXT7","spacing_WNNqbL","spacing_GJ6dRp","spacing_dextkm","button_fHNQ7J"],"name":"FROZEN ROCKET","settings":{"transparent_header":true,"image":"shopify:\/\/shop_images\/USAH_banner_homepage_desktop_2_aa0b930f-2b39-4314-9298-c6fa50413954.webp","image_height":"adapt","content_width":"small","content_position":"md:items-center md:justify-start","text_alignment":"left","image_mobile":"shopify:\/\/shop_images\/USAH_banner_homepage_MOBILE_3_f977e68f-e6c3-4bea-a9e8-5af2e2bf6a28.webp","image_height_mobile":"adapt","content_position_mobile":"items-start justify-center","text_alignment_mobile":"center","color_text":"#000000","color_background":"#000000","gradient_background":"","color_highlight":"#e2fb31","gradient_highlight":"","color_button_text":"#ffffff","color_button_background":"#ce0e2d","color_button_gradient":"","color_overlay":"#171717","overlay_opacity":0,"padding_top":0,"padding_bottom":0,"divider":false,"full_width":true,"rounded":false,"enable_parallax":false,"parallax_direction":"vertical"}},"image_with_text_overlay_9ze9nz":{"type":"image-with-text-overlay","blocks":{"spacing_ptgAi9":{"type":"spacing","settings":{"height":0,"height_mobile":12}},"image_6nKp3t":{"type":"image","settings":{"image":"shopify:\/\/shop_images\/USA_LIMITED_HOME_PAGE_2.svg","image_width":"custom","image_max_width":210,"image_max_width_mobile":160}},"spacing_LMfGYE":{"type":"spacing","settings":{"height":0,"height_mobile":100}},"spacing_3WGjxe":{"type":"spacing","disabled":true,"settings":{"height":0,"height_mobile":24}},"button_UpzgcR":{"type":"button","settings":{"button_label":"SHOP USA","button_link":"shopify:\/\/pages\/shop-by-collection","button_style":"primary","button_size":"sm","button_external":false,"button_icon":true}}},"block_order":["spacing_ptgAi9","image_6nKp3t","spacing_LMfGYE","spacing_3WGjxe","button_UpzgcR"],"disabled":true,"name":"USAH COLLECTION","settings":{"transparent_header":true,"image":"shopify:\/\/shop_images\/USAH_banner_homepage_MOBILE_3_07bd3705-1746-4180-a8dc-0c2316bd39c8.webp","image_height":"adapt","content_width":"small","content_position":"md:items-center md:justify-start","text_alignment":"left","image_mobile":"shopify:\/\/shop_images\/USAH_banner_homepage_MOBILE_3.webp","image_height_mobile":"adapt","content_position_mobile":"items-start justify-center","text_alignment_mobile":"center","color_text":"#ffffff","color_background":"#000000","gradient_background":"","color_highlight":"#e2fb31","gradient_highlight":"","color_button_text":"#ffffff","color_button_background":"#ff0000","color_button_gradient":"","color_overlay":"#171717","overlay_opacity":0,"padding_top":0,"padding_bottom":0,"divider":false,"full_width":true,"rounded":false,"enable_parallax":false,"parallax_direction":"vertical"}},"logo_list_nBVhDN":{"type":"logo-list","blocks":{"logo_cWMNeC":{"type":"logo","settings":{"height":80,"link":""}},"logo_BeiVLK":{"type":"logo","disabled":true,"settings":{"image":"shopify:\/\/shop_images\/black_safety.svg","height":80,"link":""}},"logo_bXHpfG":{"type":"logo","settings":{"image":"shopify:\/\/shop_images\/HECC_CERTIFIED_ICON_HOME_PAGE.svg","height":80,"link":"https:\/\/cdn.shopify.com\/s\/files\/1\/0635\/2401\/2210\/files\/80259263_HECC_NLP_ISO_Certificate.pdf?v=1758816670"}},"logo_qQVDHF":{"type":"logo","settings":{"image":"shopify:\/\/shop_images\/black_velcro.svg","height":80,"link":""}},"logo_gte4mJ":{"type":"logo","settings":{"image":"shopify:\/\/shop_images\/official_partner_of_usa_hockey_icon_df673b60-667f-4add-b4c0-8e6c69eca8b4.svg","height":80,"link":"shopify:\/\/pages\/usa-hockey"}},"logo_A37pVi":{"type":"logo","settings":{"image":"shopify:\/\/shop_images\/official_partner_of_PWHL_icon_5617f3fe-b1fa-4b35-81d3-ab209655649f.svg","height":80,"link":""}},"logo_jEYXJw":{"type":"logo","settings":{"image":"shopify:\/\/shop_images\/black_usa.svg","height":80,"link":""}},"logo_fhz9ah":{"type":"logo","settings":{"image":"shopify:\/\/shop_images\/black_warranty.svg","height":80,"link":""}}},"block_order":["logo_cWMNeC","logo_BeiVLK","logo_bXHpfG","logo_qQVDHF","logo_gte4mJ","logo_A37pVi","logo_jEYXJw","logo_fhz9ah"],"name":"Icons Black","settings":{"layout":"marquee","grid_horizontal":50,"direction":"left","speed":5,"heading":"","heading_size":"title-sm","heading_alignment":"text-center md:items-center","heading_tag":"h2","subheading":"","description":"","button_label":"","button_link":"","button_external":false,"button_icon":true,"highlighted_text":"none","highlighted_scribble":"circle","highlighted_reveal":false,"color_text":"","color_background":"#000000","gradient_background":"","color_highlight":"","gradient_highlight":"","color_button_text":"","color_button_background":"","color_button_gradient":"","padding_top":4,"padding_bottom":4,"divider":false,"full_width":true,"rounded":false}},"size_based_products_6ab66e":{"type":"size-based-products","name":"Size-Based Products","settings":{"heading":"SHOP BY SIZE","heading_size":"title-md","heading_alignment":"text-center md:items-center","heading_tag":"h2","tagline":"In Stock, Ready to Ship","button-text":"Select your size","preselected_size":"","heading_2":"IN STOCK BATTLEGEAR IN SIZE","source_collections":[],"heading_size_2":"title-sm","heading_alignment_2":"text-left md:items-end md:flex-row","heading_tag_2":"h2","heading_2_template":"{size} BATTLEGEAR IN STOCK","show_size_in_heading":true,"subheading_2":"","color_background_carousel":"#f2f2f2","columns":5,"carousel_on_desktop":false,"columns_mobile":"2","swipe_on_mobile":false,"color_text":"","color_background":"#e2fb31","padding_top":20,"padding_bottom":20,"divider":false,"full_width":false,"rounded":false}},"featured_collection_8C74HH":{"type":"featured-collection","settings":{"collection":"","products":["cut-resistant-baselayer-3-0-black","cut-resistant-neck-guard-3-0-black","cut-resistant-baselayer-3-0-white","cut-resistant-neck-guard-3-0-white","battlegear-2-0-cut-resistant-hockey-neck-guard-shirt-miami-long","yth-dryland-short-rl-vert","yth-rink-rat-hoodie-neon-blue","yth-flying-pucks-tee-white","sr-silky-mitts-hoodie-desert-sand","sr-dryland-short-short-1","yth-victory-tee-heather-gray","sr-dryland-short-whiteout-camo"],"product_limit":12,"columns":5,"new_version2":false,"carousel_on_desktop":true,"show_view_all":false,"columns_mobile":"2","swipe_on_mobile":true,"heading":"PLAYER FAVORITES","heading_size":"title-md","heading_alignment":"text-left md:items-end md:flex-row","heading_tag":"h2","subheading":"","description":"","highlighted_text":"full_text","highlighted_scribble":"circle","highlighted_reveal":false,"color_text":"","color_background":"#f2f2f2","gradient_background":"","color_highlight":"","gradient_highlight":"","color_button_text":"","color_button_background":"","color_button_gradient":"","padding_top":36,"padding_bottom":16,"divider":false,"full_width":false,"rounded":false}},"custom_rich_text_XqwCi6":{"type":"custom-rich-text","blocks":{"heading_part_agy7Tm":{"type":"heading_part","settings":{"text":"NOT ALL","font_style":"armour","heading_size_mobile_px":32,"heading_size_desktop_px":60,"new_line":true}},"heading_part_Kn4TGX":{"type":"heading_part","settings":{"text":"NECK GUARDS","font_style":"armour","heading_size_mobile_px":32,"heading_size_desktop_px":60,"new_line":true}},"heading_part_tgFy3a":{"type":"heading_part","settings":{"text":"ARE CREATED EQUAL","font_style":"armour","heading_size_mobile_px":32,"heading_size_desktop_px":60,"new_line":true}},"text_9hEtyk":{"type":"text","settings":{"text":"<p>Titan BattleGear delivers the highest level of cut resistance in hockey where it counts – neck and wrists. Play with confidence knowing you’re fully covered.<\/p>","text_max_width_mobile":560,"text_max_width_desktop":580,"text_font":"body","text_size":"subtext-md","text_max_size":32,"text_line_height":1.6,"text_letter_spacing":0,"text_capitalize":false,"secondary_color":false,"highlighted_text":"none","highlighted_scribble":"circle"}}},"block_order":["heading_part_agy7Tm","heading_part_Kn4TGX","heading_part_tgFy3a","text_9hEtyk"],"name":"Custom Rich Text","settings":{"text_alignment":"left","text_alignment_mobile":"left","heading":"","heading_size":"title-md","heading_alignment":"text-left md:items-end md:flex-row","heading_width":"small","heading_tag":"h2","combined_heading_tag":"h2","subheading":"","description":"","button_label":"","button_link":"","button_external":false,"button_icon":true,"highlighted_text":"none","highlighted_scribble":"circle","highlighted_reveal":false,"color_text":"","color_background":"#ffffff","gradient_background":"","color_highlight":"","gradient_highlight":"","color_button_text":"","color_button_background":"","color_button_gradient":"","padding_top":28,"padding_bottom":28,"divider":false,"narrow":false,"rounded":false}},"portfolio_custom_pKEPkB":{"type":"portfolio-custom","blocks":{"profile_Fy4DwU":{"type":"profile","settings":{"image":"shopify:\/\/shop_images\/tech_1_b54f6942-8c26-4fcd-bf2a-2de6e24a618b.png","icon":"shopify:\/\/shop_images\/spc.svg","icon_size":58,"heading":"<p>Ditch<\/p><p>Velcro<\/p>","description":"<p><strong>Patented Stretch ProCurve™ Collar<\/strong><\/p><p>Adaptive protection that moves with the athlete. No straps. No irritation. No velcro.<\/p>","text":"<p>Use this text to share information about your brand with your customers. Describe a product, share announcements, or welcome customers to your store.<\/p>","color_text":"#ffffff","color_background":"#171717"}},"profile_eM6UV4":{"type":"profile","settings":{"image":"shopify:\/\/shop_images\/tech_2_206b17d5-6051-4d44-a7d6-dea393579846.png","icon":"shopify:\/\/shop_images\/titanotex_aero_181f01f0-d378-4e30-8026-b5fdd25543cf.svg","icon_size":52,"heading":"<p>MAXIMUM<\/p><p>CUT RESISTANCE<\/p>","description":"<p><strong>TITANOTEX™ cut-resistant Fabric<\/strong><\/p><p>Rated up to ANSI A9 (scale of A1-A9), while other brands average A3.<\/p>","text":"<p>Use this text to share information about your brand with your customers. Describe a product, share announcements, or welcome customers to your store.<\/p>","color_text":"#ffffff","color_background":"#171717"}},"profile_neAyA3":{"type":"profile","settings":{"image":"shopify:\/\/shop_images\/tech_4_7d9ac665-5dd7-4c19-9d14-5419ea71ee01.png","icon":"shopify:\/\/shop_images\/arcguar_logo.svg","icon_size":52,"heading":"<p>FULL<br\/>COVERAGE<\/p>","description":"<p><strong>Patented Arc~Guard™ Collar<\/strong><\/p><p>Anatomically contoured to protect the carotid and jugular without bunching.<\/p>","text":"<p>Use this text to share information about your brand with your customers. Describe a product, share announcements, or welcome customers to your store.<\/p>","color_text":"#ffffff","color_background":"#171717"}},"profile_63GDU3":{"type":"profile","settings":{"image":"shopify:\/\/shop_images\/13.png","icon":"shopify:\/\/shop_images\/comfort.svg","icon_size":54,"heading":"<p>LIGHTWEIGHT<\/p><p>& BREATHABLE<\/p>","description":"<p>Thermo-regulated 4-way stretch fabric, engineered to wick moisture and provide maximum mobility.<\/p>","text":"<p>Use this text to share information about your brand with your customers. Describe a product, share announcements, or welcome customers to your store.<\/p>","color_text":"#ffffff","color_background":"#171717"}},"profile_ENxBHe":{"type":"profile","settings":{"image":"shopify:\/\/shop_images\/tech_5_8c112124-d850-4eb2-8a7a-f570e984cdfa.png","icon":"shopify:\/\/shop_images\/style_logo.svg","icon_size":52,"heading":"<p>UNMATCHED<br\/>STYLE<\/p>","description":"<p>Express your identity with bold designs, limited edition drops, and team colors. <\/p>","text":"<p>Use this text to share information about your brand with your customers. Describe a product, share announcements, or welcome customers to your store.<\/p>","color_text":"#ffffff","color_background":"#171717"}},"profile_G6qWhk":{"type":"profile","settings":{"image":"shopify:\/\/shop_images\/tech_6_490391e4-5fdf-4b86-8c7f-303f089b6315.png","icon":"shopify:\/\/shop_images\/usa_logo.svg","icon_size":52,"heading":"<p>MADE IN<br\/>THE USA<\/p>","description":"<p>Built locally <strong>(MN, NJ, FL)<\/strong>, with the best materials. Protection that doesn't need a passport.<\/p>","text":"<p>Use this text to share information about your brand with your customers. Describe a product, share announcements, or welcome customers to your store.<\/p>","color_text":"#ffffff","color_background":"#171717"}},"profile_xzgaB6":{"type":"profile","settings":{"image":"shopify:\/\/shop_images\/7_b38fd5c8-4233-4272-890f-0e026399ae6d.jpg","icon":"shopify:\/\/shop_images\/teamworks_logo.svg","icon_size":44,"heading":"<p>YOUR TEAM<br\/>YOUR COLORS<\/p>","description":"<p><strong>Custom Team Baselayer<\/strong><\/p><p>Designed with your team's logo, colors, and unique identity.<\/p>","text":"<p>Use this text to share information about your brand with your customers. Describe a product, share announcements, or welcome customers to your store.<\/p>","color_text":"#ffffff","color_background":"#171717"}}},"block_order":["profile_Fy4DwU","profile_eM6UV4","profile_neAyA3","profile_63GDU3","profile_ENxBHe","profile_G6qWhk","profile_xzgaB6"],"name":"Tech Specs","settings":{"columns":5,"carousel_on_desktop":true,"layout":"default","image_ratio":"portrait","image_ratio_mobile":"adapt","custom_image_height":"","columns_mobile":"1","swipe_on_mobile":true,"disable_modal_opening":true,"color_text":"","color_background":"#ffffff","gradient_background":"","color_highlight":"","gradient_highlight":"","color_button_text":"","color_button_background":"","color_button_gradient":"","padding_top":24,"padding_bottom":36,"divider":false,"full_width":false,"rounded":false}},"image_with_text_overlay_D63Y7B":{"type":"image-with-text-overlay","blocks":{"heading_dc4TJK":{"type":"heading","settings":{"heading":"MAXIMUM CUT-RESISTANCE","heading_size":"title-md","heading_tag":"h2","highlighted_text":"none","highlighted_scribble":"circle","highlighted_reveal":false}},"text_q9iPXF":{"type":"text","settings":{"text":"<p>11 of 14 other neck guards failed to stop a skate blade in lab testing<\/p><p><a href=\"https:\/\/www.titanbattlegear.com\/blogs\/hockey-safety\/mayo-clinic-hockey-neck-guard-safety-test\" target=\"_blank\" title=\"https:\/\/www.titanbattlegear.com\/blogs\/hockey-safety\/mayo-clinic-hockey-neck-guard-safety-test\"><em>Mayo Clinic \/ Clinical Journal of Sports Medicine.<\/em><\/a><\/p>","text_font":"body","text_size":"subtext-md","text_max_size":32,"text_line_height":1.6,"text_letter_spacing":0,"text_capitalize":false,"secondary_color":false,"highlighted_text":"none","highlighted_scribble":"circle"}},"image_zVGkAL":{"type":"image","settings":{"image":"shopify:\/\/shop_images\/safety_scale_jun_2026_black.svg","image_width":"custom","image_max_width":600,"image_max_width_mobile":380}}},"block_order":["heading_dc4TJK","text_q9iPXF","image_zVGkAL"],"name":"new safety scale section","settings":{"transparent_header":false,"image":"shopify:\/\/shop_images\/tech_safety_scale_header.png","image_height":"adapt","content_width":"small","content_position":"md:items-center md:justify-start","text_alignment":"left","image_mobile":"shopify:\/\/shop_images\/tech_safety_scale_header_mobile.png","image_height_mobile":"600px","content_position_mobile":"items-start justify-start","text_alignment_mobile":"left","color_text":"#ffffff","color_background":"#171717","gradient_background":"","color_highlight":"#e2fb31","gradient_highlight":"","color_button_text":"#171717","color_button_background":"#ffffff","color_button_gradient":"","color_overlay":"#171717","overlay_opacity":0,"padding_top":0,"padding_bottom":0,"divider":false,"full_width":true,"rounded":false,"enable_parallax":false,"parallax_direction":"vertical"}},"custom_rich_text_z9ewr3":{"type":"custom-rich-text","blocks":{"heading_part_wja6JW":{"type":"heading_part","settings":{"text":"UPGRADE TO TITAN","font_style":"armour","heading_size_mobile_px":32,"heading_size_desktop_px":60,"new_line":false}}},"block_order":["heading_part_wja6JW"],"name":"Custom Rich Text","settings":{"text_alignment":"left","text_alignment_mobile":"left","heading":"","heading_size":"title-md","heading_alignment":"text-left md:items-end md:flex-row","heading_width":"small","heading_tag":"h2","combined_heading_tag":"h2","subheading":"","description":"","button_label":"","button_link":"","button_external":false,"button_icon":true,"highlighted_text":"none","highlighted_scribble":"circle","highlighted_reveal":false,"color_text":"","color_background":"#ffffff","gradient_background":"","color_highlight":"","gradient_highlight":"","color_button_text":"","color_button_background":"","color_button_gradient":"","padding_top":60,"padding_bottom":40,"divider":false,"narrow":false,"rounded":false}},"titanpdp_comparison_table_RBJzWh":{"type":"titanpdpComparisonTable","name":"Titan PDP Compare Table","settings":{"margin_top":10,"margin_bottom":75,"color_background":"#ffffff","swap_row_color_order":true,"gray_row_color":"#ffffff","white_row_color":"#f2f2f2"}},"image_with_text_overlay_ccefpm":{"type":"image-with-text-overlay","blocks":{"image_j9xdgH":{"type":"image","settings":{"image":"shopify:\/\/shop_images\/frozen_rocket_svg_website.svg","image_width":"custom","image_max_width":230,"image_max_width_mobile":140}},"text_exaxBC":{"type":"text","disabled":true,"settings":{"text":"<p>At <strong>Titan Labs <\/strong>we don’t just create gear; we create confidence. Our commitment to innovation, protection, and performance ensures you’re always ready for the fight ahead.<\/p>","text_font":"body","text_size":"subtext-md","text_max_size":32,"text_line_height":1.6,"text_letter_spacing":0,"text_capitalize":false,"secondary_color":false,"highlighted_text":"none","highlighted_scribble":"circle"}}},"block_order":["image_j9xdgH","text_exaxBC"],"name":"FROZEN ROCKET BANNER","settings":{"transparent_header":false,"image":"shopify:\/\/shop_images\/frozen_banner_1_desk.webp","image_height":"adapt","content_width":"small","content_position":"md:items-center md:justify-start","text_alignment":"left","image_mobile":"shopify:\/\/shop_images\/frozen_banner_1_mobile.webp","image_height_mobile":"adapt","content_position_mobile":"items-start justify-center","text_alignment_mobile":"center","color_text":"#ffffff","color_background":"","gradient_background":"","color_highlight":"#00adee","gradient_highlight":"","color_button_text":"#171717","color_button_background":"#ffffff","color_button_gradient":"","color_overlay":"#171717","overlay_opacity":0,"padding_top":0,"padding_bottom":0,"divider":false,"full_width":true,"rounded":false,"enable_parallax":false,"parallax_direction":"vertical"}},"featured_collection_GBFe6r":{"type":"featured-collection","custom_css":["@media (max-width: 768px) {.title-md {font-size: var(--title-sm); \/* Adjust to your desired small size variable *\/ }}",".product-card__bottom.flex.items-center.gap-2 {display: none !important;}"],"name":"USA HOCKEY PRODUCTS","settings":{"collection":"","products":["cut-resistant-baselayer-3-0-frozen-rocket","yth-dryland-short-frozen-rocket","yth-frozen-rocket-tee-bold-blue","yth-frozen-rocket-hoodie-white","sr-dryland-short-frozen-rocket","sr-frozen-rocket-tee-bold-blue","sr-frozen-rocket-hoodie-lunar-rock"],"product_limit":25,"columns":5,"new_version2":false,"carousel_on_desktop":true,"show_view_all":true,"columns_mobile":"2","swipe_on_mobile":true,"heading":"","heading_size":"title-md","heading_alignment":"text-left md:items-end md:flex-row","heading_tag":"h2","subheading":"","description":"","highlighted_text":"none","highlighted_scribble":"circle","highlighted_reveal":false,"color_text":"","color_background":"","gradient_background":"","color_highlight":"","gradient_highlight":"","color_button_text":"","color_button_background":"","color_button_gradient":"","padding_top":28,"padding_bottom":48,"divider":false,"full_width":false,"rounded":false}},"image_with_text_overlay_R7zCJm":{"type":"image-with-text-overlay","blocks":{"image_4frnLB":{"type":"image","settings":{"image":"shopify:\/\/shop_images\/USA_LIMITED_EDITION.svg","image_width":"custom","image_max_width":230,"image_max_width_mobile":140}},"text_ReXaNE":{"type":"text","disabled":true,"settings":{"text":"<p>At <strong>Titan Labs <\/strong>we don’t just create gear; we create confidence. Our commitment to innovation, protection, and performance ensures you’re always ready for the fight ahead.<\/p>","text_font":"body","text_size":"subtext-md","text_max_size":32,"text_line_height":1.6,"text_letter_spacing":0,"text_capitalize":false,"secondary_color":false,"highlighted_text":"none","highlighted_scribble":"circle"}}},"block_order":["image_4frnLB","text_ReXaNE"],"name":"USA ANNIVERSARY BANNER","settings":{"transparent_header":false,"image":"shopify:\/\/shop_images\/USAH_banner_homepage_desktop.webp","image_height":"adapt","content_width":"small","content_position":"md:items-center md:justify-start","text_alignment":"left","image_mobile":"shopify:\/\/shop_images\/USAH_banner_homepage_MOBILE.webp","image_height_mobile":"adapt","content_position_mobile":"items-start justify-center","text_alignment_mobile":"center","color_text":"#ffffff","color_background":"","gradient_background":"","color_highlight":"#00adee","gradient_highlight":"","color_button_text":"#171717","color_button_background":"#ffffff","color_button_gradient":"","color_overlay":"#171717","overlay_opacity":0,"padding_top":0,"padding_bottom":0,"divider":false,"full_width":true,"rounded":false,"enable_parallax":false,"parallax_direction":"vertical"}},"featured_collection_XNVhWa":{"type":"featured-collection","custom_css":["@media (max-width: 768px) {.title-md {font-size: var(--title-sm); \/* Adjust to your desired small size variable *\/ }}",".product-card__bottom.flex.items-center.gap-2 {display: none !important;}"],"name":"USA HOCKEY PRODUCTS","settings":{"collection":"","products":["cut-resistant-baselayer-3-0-usa-hockey-white","yth-dryland-short-team-usa-royal","yth-usa-hockey-victory-tee-white","yth-usa-hockey-arch-tee-red","yth-usa-arch-hoodie-carolina","sr-dryland-short-team-usa-royal","sr-usa-hockey-victory-tee-white","sr-usa-hockey-arch-tee-red","sr-usa-arch-hoodie-pigment-carolina"],"product_limit":25,"columns":5,"new_version2":false,"carousel_on_desktop":true,"show_view_all":true,"columns_mobile":"2","swipe_on_mobile":true,"heading":"","heading_size":"title-md","heading_alignment":"text-left md:items-end md:flex-row","heading_tag":"h2","subheading":"","description":"","highlighted_text":"none","highlighted_scribble":"circle","highlighted_reveal":false,"color_text":"","color_background":"","gradient_background":"","color_highlight":"","gradient_highlight":"","color_button_text":"","color_button_background":"","color_button_gradient":"","padding_top":28,"padding_bottom":48,"divider":false,"full_width":false,"rounded":false}},"image_with_text_overlay_7TRTMy":{"type":"image-with-text-overlay","blocks":{"liquid_tFRYWR":{"type":"liquid","disabled":true,"settings":{"liquid":"{% if customer and customer.tags contains 'B2B' %}\n  <h1 style=\"font-size: var(--title-md) font-family: 'TITANFONT';\">Welcome to Wholesale TitanBattlegear<\/h1>\n{% else %}\n  <h1 style=\"font-size: var(--title-md)font-family: 'TITANFONT';\">NOT ALL NECK GUARDS ARE CREATED EQUAL<\/h1>\n{% endif %}"}},"button_Qn6pFx":{"type":"button","disabled":true,"settings":{"button_label":"PREORDER NOW","button_link":"shopify:\/\/pages\/team-colors-battlegear","button_style":"primary","button_size":"sm","button_external":true,"button_icon":true}},"subheading_fCNN6e":{"type":"subheading","disabled":true,"settings":{"subheading":"GEAR UP FOR THE UPCOMING SEASON","subheading_size":"subtitle-lg","secondary_color":true}},"heading_aGcQEy":{"type":"heading","settings":{"heading":"RINKWEAR","heading_size":"title-lg tracking-heading","heading_tag":"h2","highlighted_text":"none","highlighted_scribble":"circle","highlighted_reveal":false}},"text_amQBy8":{"type":"text","disabled":true,"settings":{"text":"<p>Built for performance. Powered by innovation.<\/p>","text_font":"body","text_size":"subtext-md","text_max_size":32,"text_line_height":1.6,"text_letter_spacing":0,"text_capitalize":false,"secondary_color":false,"highlighted_text":"none","highlighted_scribble":"circle"}}},"block_order":["liquid_tFRYWR","button_Qn6pFx","subheading_fCNN6e","heading_aGcQEy","text_amQBy8"],"settings":{"transparent_header":true,"image":"shopify:\/\/shop_images\/classic_banner_james_hagens_hoodie_desktop_d29b8f5e-e797-4a94-85f2-b267d443b612.png","image_height":"adapt","content_width":"large","content_position":"md:items-end md:justify-start","text_alignment":"left","image_mobile":"shopify:\/\/shop_images\/classic_banner_james_hagens_hoodie_mobile_6ecfddec-5596-4e66-a8b6-960a2c535b4e.png","image_height_mobile":"adapt","content_position_mobile":"items-end justify-start","text_alignment_mobile":"left","color_text":"#ffffff","color_background":"","gradient_background":"","color_highlight":"#e2fb31","gradient_highlight":"","color_button_text":"#171717","color_button_background":"#ffffff","color_button_gradient":"","color_overlay":"#171717","overlay_opacity":6,"padding_top":0,"padding_bottom":0,"divider":false,"full_width":true,"rounded":false,"enable_parallax":false,"parallax_direction":"vertical"}},"featured_collections_6azE9V":{"type":"featured-collections","blocks":{"collection_etwJ8i":{"type":"collection","settings":{"collection":"graphic-yth-hoodie","products":[],"title":"GRAPHIC HOODIES"}},"collection_wHDTQ4":{"type":"collection","settings":{"collection":"graphic-yth-tee","products":[],"title":"GRAPHIC TEES"}},"collection_RqU7yn":{"type":"collection","settings":{"collection":"shorts","products":[],"title":""}},"collection_nGBkJj":{"type":"collection","settings":{"collection":"hats","products":[],"title":""}}},"block_order":["collection_etwJ8i","collection_wHDTQ4","collection_RqU7yn","collection_nGBkJj"],"name":"Multiple featured collections","settings":{"product_limit":12,"columns":5,"carousel_on_desktop":true,"show_view_all":false,"columns_mobile":"2","swipe_on_mobile":true,"heading":"","heading_size":"title-lg tracking-heading","heading_alignment":"text-left md:items-end md:flex-row","heading_tag":"h2","subheading":"","description":"","highlighted_text":"none","highlighted_scribble":"circle","highlighted_reveal":false,"color_text":"","color_background":"","gradient_background":"","color_highlight":"","gradient_highlight":"","color_button_text":"","color_button_background":"#00adee","color_button_gradient":"","padding_top":44,"padding_bottom":20,"divider":false,"full_width":false,"rounded":false}},"shop_the_feed_JmignW":{"type":"shop-the-feed","blocks":{"feed_rBYxdM":{"type":"feed","settings":{"image":"shopify:\/\/shop_images\/royal_c34772cc-2eb6-453d-8994-37477cca94e3.jpg","enable_video_autoplay":true,"enable_video_looping":true,"video_on_hover":true,"button_label":"View","button_link":"","button_external":true,"button_icon":true,"account_avatar":"shopify:\/\/shop_images\/youtube_profile_pic.png","account_name":"@Titan_Battlegear","account_description":"Not All Neck Guards Are Created Equal.","account_button":"Follow","account_link":"https:\/\/www.instagram.com\/titan_battlegear\/","account_link_external":false,"color_text":"#ffffff","color_button_text":"#000000","color_button_background":"#ffffff","color_button_gradient":"","hotspot_color_text_1":"#ffffff","hotspot_vertical_1":57,"hotspot_horizontal_1":53,"hotspot_product_1":"battlegear-2-0-cut-resistant-hockey-neck-guard-shirt-team-royal-long","hotspot_color_text_2":"#ffffff","hotspot_vertical_2":40,"hotspot_horizontal_2":52,"hotspot_product_2":"","hotspot_color_text_3":"#ffffff","hotspot_vertical_3":60,"hotspot_horizontal_3":75,"hotspot_product_3":"","hotspot_color_text_4":"#ffffff","hotspot_vertical_4":50,"hotspot_horizontal_4":50,"hotspot_product_4":""}},"feed_FzaDwB":{"type":"feed","settings":{"image":"shopify:\/\/shop_images\/logan_ambassador-3.jpg","enable_video_autoplay":true,"enable_video_looping":true,"video_on_hover":true,"button_label":"View","button_link":"","button_external":true,"button_icon":true,"account_avatar":"shopify:\/\/shop_images\/youtube_profile_pic.png","account_name":"@Titan_Battlegear","account_description":"Not All Neck Guards Are Created Equal.","account_button":"Follow","account_link":"https:\/\/www.instagram.com\/titan_battlegear\/","account_link_external":false,"color_text":"#ffffff","color_button_text":"#000000","color_button_background":"#ffffff","color_button_gradient":"","hotspot_color_text_1":"#ffffff","hotspot_vertical_1":61,"hotspot_horizontal_1":25,"hotspot_product_1":"hockey-shirt-with-neck-guard-youth-arc-guard","hotspot_color_text_2":"#ffffff","hotspot_vertical_2":40,"hotspot_horizontal_2":52,"hotspot_product_2":"","hotspot_color_text_3":"#ffffff","hotspot_vertical_3":60,"hotspot_horizontal_3":75,"hotspot_product_3":"","hotspot_color_text_4":"#ffffff","hotspot_vertical_4":50,"hotspot_horizontal_4":50,"hotspot_product_4":""}},"feed_JcmBNa":{"type":"feed","settings":{"image":"shopify:\/\/shop_images\/AJA_CHAMPION_RING_red-3.jpg","enable_video_autoplay":true,"enable_video_looping":true,"video_on_hover":true,"button_label":"View","button_link":"","button_external":true,"button_icon":true,"account_avatar":"shopify:\/\/shop_images\/youtube_profile_pic.png","account_name":"@Titan_Battlegear","account_description":"Not All Neck Guards Are Created Equal.","account_button":"Follow","account_link":"https:\/\/www.instagram.com\/titan_battlegear\/","account_link_external":false,"color_text":"#ffffff","color_button_text":"#000000","color_button_background":"#ffffff","color_button_gradient":"","hotspot_color_text_1":"#ffffff","hotspot_vertical_1":48,"hotspot_horizontal_1":53,"hotspot_product_1":"battlegear-2-0-cut-resistant-hockey-neck-guard-shirt-team-red-long","hotspot_color_text_2":"#ffffff","hotspot_vertical_2":40,"hotspot_horizontal_2":52,"hotspot_product_2":"","hotspot_color_text_3":"#ffffff","hotspot_vertical_3":60,"hotspot_horizontal_3":75,"hotspot_product_3":"","hotspot_color_text_4":"#ffffff","hotspot_vertical_4":50,"hotspot_horizontal_4":50,"hotspot_product_4":""}},"feed_gxGMMa":{"type":"feed","settings":{"image":"shopify:\/\/shop_images\/two_boys_in_locker_room_2.jpg","enable_video_autoplay":true,"enable_video_looping":true,"video_on_hover":true,"button_label":"View","button_link":"","button_external":true,"button_icon":true,"account_avatar":"shopify:\/\/shop_images\/youtube_profile_pic.png","account_name":"@Titan_Battlegear","account_description":"Not All Neck Guards Are Created Equal.","account_button":"Follow","account_link":"https:\/\/www.instagram.com\/titan_battlegear\/","account_link_external":false,"color_text":"#ffffff","color_button_text":"#000000","color_button_background":"#ffffff","color_button_gradient":"","hotspot_color_text_1":"#ffffff","hotspot_vertical_1":51,"hotspot_horizontal_1":26,"hotspot_product_1":"battlegear-2-0-cut-resistant-hockey-neck-guard-shirt-miami-long","hotspot_color_text_2":"#ffffff","hotspot_vertical_2":55,"hotspot_horizontal_2":69,"hotspot_product_2":"battlegear-2-0-cut-resistant-hockey-neck-guard-shirt-arctic-long","hotspot_color_text_3":"#ffffff","hotspot_vertical_3":60,"hotspot_horizontal_3":75,"hotspot_product_3":"","hotspot_color_text_4":"#ffffff","hotspot_vertical_4":50,"hotspot_horizontal_4":50,"hotspot_product_4":""}}},"block_order":["feed_rBYxdM","feed_FzaDwB","feed_JcmBNa","feed_gxGMMa"],"name":"t:sections.shop-the-feed.name","settings":{"columns":4,"carousel_on_desktop":true,"image_ratio":"portrait","columns_mobile":"1","swipe_on_mobile":true,"account_avatar":"shopify:\/\/shop_images\/youtube_profile_pic.png","account_name":"@titan_battlegear","show_vendor":false,"show_price":true,"heading":"SHOP THE LOOK","heading_size":"title-md","heading_alignment":"text-left md:items-end md:flex-row","heading_tag":"h2","subheading":"","description":"<p>See how real players – our Brand Ambassadors – wear Titan.<\/p>","button_label":"Follow","button_link":"https:\/\/www.instagram.com\/titan_battlegear\/","button_external":true,"button_icon":true,"highlighted_text":"none","highlighted_scribble":"circle","highlighted_reveal":false,"color_text":"","color_background":"","gradient_background":"","color_highlight":"","gradient_highlight":"","color_button_text":"","color_button_background":"","color_button_gradient":"","padding_top":60,"padding_bottom":60,"divider":false,"full_width":false,"rounded":false}},"testimonials_banner_aUWWwz":{"type":"testimonials-banner","blocks":{"testimonial_KeHtMt":{"type":"testimonial","settings":{"icon":"quote","text":"<p>This is easily the best product on the market for <em>motion, dexterity, protection<\/em> and feel that I have seen.<\/p>","author":"Matt J.","author_info":"","author_url":"","image_ratio":"rounded","image_height":30,"highlighted_text":"text","highlighted_scribble":"circle"}},"testimonial_P7BtXB":{"type":"testimonial","settings":{"icon":"quote","text":"<p>My son <em>absolutely loves the fit<\/em> of these shirts. We have bought three so far and they are all in great shape even after a year of washing them every week.\"<\/p>","author":"Helen V.","author_info":"","author_url":"","image_ratio":"rounded","image_height":30,"highlighted_text":"text","highlighted_scribble":"circle"}},"testimonial_XqUgeX":{"type":"testimonial","settings":{"icon":"quote","text":"<p>This is the <em>best neck protection<\/em> I’ve tried. The other brands I have tried pulled my hair out from the Velcro. I tried to wear it different ways to avoid it getting in the way but it never helped. These pull over Titan ones are a <em>game changer<\/em><\/p>","author":"Heather W.","author_info":"","author_url":"","image_ratio":"rounded","image_height":30,"highlighted_text":"text","highlighted_scribble":"circle"}},"testimonial_Nex3d7":{"type":"testimonial","settings":{"icon":"quote","text":"<p>My son lives in his Titan shirts. He loves them, and never complains about having to wear neck protection anymore. Thank you, Titan Battlegear, for making <em>such a great product<\/em>!!<\/p>","author":"Kristie B.","author_info":"","author_url":"","image_ratio":"rounded","image_height":30,"highlighted_text":"text","highlighted_scribble":"circle"}},"testimonial_iKxG4y":{"type":"testimonial","settings":{"icon":"quote","text":"<p>This is the <em>best neck protection I’ve tried. <\/em>The other brands I have tried pulled my hair out from the Velcro.  These pull over Titan ones are a game changer!<\/p>","author":"Heather W","author_info":"","author_url":"","image_ratio":"rounded","image_height":30,"highlighted_text":"text","highlighted_scribble":"circle"}}},"block_order":["testimonial_KeHtMt","testimonial_P7BtXB","testimonial_XqUgeX","testimonial_Nex3d7","testimonial_iKxG4y"],"name":"Testimonials banner","settings":{"transparent_header":false,"image":"shopify:\/\/shop_images\/review_jugando_hockey-3.jpg","image_height":"650px","content_position":"md:items-center md:justify-center","image_height_mobile":"500px","content_position_mobile":"items-center justify-center","color_text":"#ffffff","color_background":"","gradient_background":"","color_highlight":"#e2fb31","gradient_highlight":"","color_overlay":"#171717","overlay_opacity":75,"padding_top":0,"padding_bottom":0,"divider":false,"full_width":true,"rounded":false,"enable_parallax":true,"parallax_direction":"vertical"}},"image_with_text_overlay_JRDjRF":{"type":"image-with-text-overlay","blocks":{"button_qipicF":{"type":"button","settings":{"button_label":"LEARN MORE","button_link":"shopify:\/\/blogs\/hockey-safety\/titan-made-in-the-usa","button_style":"primary","button_size":"sm","button_external":false,"button_icon":false}}},"block_order":["button_qipicF"],"settings":{"transparent_header":false,"image":"shopify:\/\/shop_images\/st_paul_banner_06be372a-0b77-44b0-8711-84d863c591b3.png","image_height":"adapt","content_width":"small","content_position":"md:items-end md:justify-center","text_alignment":"left","image_mobile":"shopify:\/\/shop_images\/st_paul_banner_1_a8396a4a-8a0f-4616-a9eb-c548d7325f48.png","image_height_mobile":"adapt","content_position_mobile":"items-end justify-center","text_alignment_mobile":"center","color_text":"#ffffff","color_background":"","gradient_background":"","color_highlight":"#e0a580","gradient_highlight":"","color_button_text":"#171717","color_button_background":"#ffffff","color_button_gradient":"","color_overlay":"#171717","overlay_opacity":0,"padding_top":0,"padding_bottom":0,"divider":false,"full_width":true,"rounded":false,"enable_parallax":false,"parallax_direction":"vertical"}}},"order":["image_with_text_overlay_XyHULG","image_with_text_overlay_9ze9nz","logo_list_nBVhDN","size_based_products_6ab66e","featured_collection_8C74HH","custom_rich_text_XqwCi6","portfolio_custom_pKEPkB","image_with_text_overlay_D63Y7B","custom_rich_text_z9ewr3","titanpdp_comparison_table_RBJzWh","image_with_text_overlay_ccefpm","featured_collection_GBFe6r","image_with_text_overlay_R7zCJm","featured_collection_XNVhWa","image_with_text_overlay_7TRTMy","featured_collections_6azE9V","shop_the_feed_JmignW","testimonials_banner_aUWWwz","image_with_text_overlay_JRDjRF"]}